<annotation>
	<folder></folder>
	<filename>104dbd4912151645_jpg.rf.d080ef4188b9ef9524ee9de84d972ea2.jpg</filename>
	<path>104dbd4912151645_jpg.rf.d080ef4188b9ef9524ee9de84d972ea2.jpg</path>
	<source>
		<database>roboflow.ai</database>
	</source>
	<size>
		<width>1024</width>
		<height>768</height>
		<depth>3</depth>
	</size>
	<segmented>0</segmented>
	<object>
		<name>0</name>
		<pose>Unspecified</pose>
		<truncated>0</truncated>
		<difficult>0</difficult>
		<occluded>0</occluded>
		<bndbox>
			<xmin>677</xmin>
			<xmax>729</xmax>
			<ymin>699</ymin>
			<ymax>722</ymax>
		</bndbox>
	</object>
</annotation>
