<annotation>
	<folder></folder>
	<filename>1550b198e01907d7_jpg.rf.679d385350b618d6814b5ca3e91106d8.jpg</filename>
	<path>1550b198e01907d7_jpg.rf.679d385350b618d6814b5ca3e91106d8.jpg</path>
	<source>
		<database>roboflow.ai</database>
	</source>
	<size>
		<width>1024</width>
		<height>768</height>
		<depth>3</depth>
	</size>
	<segmented>0</segmented>
	<object>
		<name>0</name>
		<pose>Unspecified</pose>
		<truncated>0</truncated>
		<difficult>0</difficult>
		<occluded>0</occluded>
		<bndbox>
			<xmin>98</xmin>
			<xmax>123</xmax>
			<ymin>337</ymin>
			<ymax>350</ymax>
		</bndbox>
	</object>
	<object>
		<name>0</name>
		<pose>Unspecified</pose>
		<truncated>0</truncated>
		<difficult>0</difficult>
		<occluded>0</occluded>
		<bndbox>
			<xmin>299</xmin>
			<xmax>324</xmax>
			<ymin>363</ymin>
			<ymax>378</ymax>
		</bndbox>
	</object>
</annotation>
