<annotation>
	<folder></folder>
	<filename>650ae7efc646157f_jpg.rf.29d494bafd1e159c9e18778f75eef672.jpg</filename>
	<path>650ae7efc646157f_jpg.rf.29d494bafd1e159c9e18778f75eef672.jpg</path>
	<source>
		<database>roboflow.ai</database>
	</source>
	<size>
		<width>1024</width>
		<height>768</height>
		<depth>3</depth>
	</size>
	<segmented>0</segmented>
	<object>
		<name>0</name>
		<pose>Unspecified</pose>
		<truncated>0</truncated>
		<difficult>0</difficult>
		<occluded>0</occluded>
		<bndbox>
			<xmin>223</xmin>
			<xmax>727</xmax>
			<ymin>359</ymin>
			<ymax>606</ymax>
		</bndbox>
	</object>
</annotation>
