<annotation>
	<folder></folder>
	<filename>86fb78d50864a51d_jpg.rf.c20239d3c7a86ac7d7d3b696490ad8c0.jpg</filename>
	<path>86fb78d50864a51d_jpg.rf.c20239d3c7a86ac7d7d3b696490ad8c0.jpg</path>
	<source>
		<database>roboflow.ai</database>
	</source>
	<size>
		<width>1024</width>
		<height>768</height>
		<depth>3</depth>
	</size>
	<segmented>0</segmented>
	<object>
		<name>0</name>
		<pose>Unspecified</pose>
		<truncated>0</truncated>
		<difficult>0</difficult>
		<occluded>0</occluded>
		<bndbox>
			<xmin>573</xmin>
			<xmax>601</xmax>
			<ymin>642</ymin>
			<ymax>653</ymax>
		</bndbox>
	</object>
	<object>
		<name>0</name>
		<pose>Unspecified</pose>
		<truncated>0</truncated>
		<difficult>0</difficult>
		<occluded>0</occluded>
		<bndbox>
			<xmin>741</xmin>
			<xmax>786</xmax>
			<ymin>615</ymin>
			<ymax>638</ymax>
		</bndbox>
	</object>
	<object>
		<name>0</name>
		<pose>Unspecified</pose>
		<truncated>0</truncated>
		<difficult>0</difficult>
		<occluded>0</occluded>
		<bndbox>
			<xmin>997</xmin>
			<xmax>1024</xmax>
			<ymin>619</ymin>
			<ymax>640</ymax>
		</bndbox>
	</object>
</annotation>
