<annotation>
	<folder></folder>
	<filename>8f9e3deca4814ee7_jpg.rf.a96319d126de9eeea2279892c29ec69c.jpg</filename>
	<path>8f9e3deca4814ee7_jpg.rf.a96319d126de9eeea2279892c29ec69c.jpg</path>
	<source>
		<database>roboflow.ai</database>
	</source>
	<size>
		<width>1024</width>
		<height>683</height>
		<depth>3</depth>
	</size>
	<segmented>0</segmented>
	<object>
		<name>0</name>
		<pose>Unspecified</pose>
		<truncated>0</truncated>
		<difficult>0</difficult>
		<occluded>0</occluded>
		<bndbox>
			<xmin>217</xmin>
			<xmax>325</xmax>
			<ymin>407</ymin>
			<ymax>432</ymax>
		</bndbox>
	</object>
	<object>
		<name>0</name>
		<pose>Unspecified</pose>
		<truncated>0</truncated>
		<difficult>0</difficult>
		<occluded>0</occluded>
		<bndbox>
			<xmin>761</xmin>
			<xmax>839</xmax>
			<ymin>432</ymin>
			<ymax>458</ymax>
		</bndbox>
	</object>
</annotation>
