<annotation>
	<folder></folder>
	<filename>e30cf3f731873ed4_jpg.rf.846e98cd7b96e53561973023469891ac.jpg</filename>
	<path>e30cf3f731873ed4_jpg.rf.846e98cd7b96e53561973023469891ac.jpg</path>
	<source>
		<database>roboflow.ai</database>
	</source>
	<size>
		<width>1024</width>
		<height>683</height>
		<depth>3</depth>
	</size>
	<segmented>0</segmented>
	<object>
		<name>0</name>
		<pose>Unspecified</pose>
		<truncated>0</truncated>
		<difficult>0</difficult>
		<occluded>0</occluded>
		<bndbox>
			<xmin>938</xmin>
			<xmax>996</xmax>
			<ymin>396</ymin>
			<ymax>419</ymax>
		</bndbox>
	</object>
</annotation>
